setup.cfg
setup.py
Optim_meth_anar/__init__.py
Optim_meth_anar.egg-info/PKG-INFO
Optim_meth_anar.egg-info/SOURCES.txt
Optim_meth_anar.egg-info/dependency_links.txt
Optim_meth_anar.egg-info/not-zip-safe
Optim_meth_anar.egg-info/top_level.txt
Optim_meth_anar/utils/Lagrange.py
Optim_meth_anar/utils/__init__.py
Optim_meth_anar/utils/brent.py
Optim_meth_anar/utils/golden_ratio.py
Optim_meth_anar/utils/gradient_descent_fixed.py
Optim_meth_anar/utils/local_extrema.py
Optim_meth_anar/utils/parabolic_interpolation.py
Optim_meth_anar/utils/parse__restr_function.py
Optim_meth_anar/utils/parse_restriction.py
Optim_meth_anar/utils/parse_variables.py
Optim_meth_anar/utils/parse_variables_tz2.py
Optim_meth_anar/utils/parser_task.py
Optim_meth_anar/utils/plot.py
Optim_meth_anar/utils/plot_tz2.py
Optim_meth_anar/utils/tz4.py
Optim_meth_anar/utils/Lagrange.py
Optim_meth_anar/utils/__init__.py
Optim_meth_anar/utils/brent.py
Optim_meth_anar/utils/golden_ratio.py
Optim_meth_anar/utils/gradient_descent_fixed.py
Optim_meth_anar/utils/local_extrema.py
Optim_meth_anar/utils/parabolic_interpolation.py
Optim_meth_anar/utils/parse__restr_function.py
Optim_meth_anar/utils/parse_restriction.py
Optim_meth_anar/utils/parse_variables.py
Optim_meth_anar/utils/parse_variables_tz2.py
Optim_meth_anar/utils/parser_task.py
Optim_meth_anar/utils/plot.py
Optim_meth_anar/utils/plot_tz2.py
Optim_meth_anar/utils/tz4.py