Metadata-Version: 2.1
Name: Optim-meth-anar
Version: 0.0.9.4
Summary: abc
Home-page: UNKNOWN
Author-email: anariem@mail.ru
License: UNKNOWN
Platform: UNKNOWN
